mixpresplit/README.md
mixpresplit/__init__.py
mixpresplit/cli.py
mixpresplit-0.1.8.dist-info/LICENSE
mixpresplit-0.1.8.dist-info/METADATA
mixpresplit-0.1.8.dist-info/WHEEL
mixpresplit-0.1.8.dist-info/entry_points.txt
mixpresplit-0.1.8.dist-info/RECORD
